AerospikeClientMock/AerospikeClientMock.py
AerospikeClientMock/AerospikeData.py
AerospikeClientMock/AerospikePredicatesMock.py
AerospikeClientMock/AerospikeQueryMock.py
AerospikeClientMock/AerospikeScanMock.py
AerospikeClientMock/__init__.py
AerospikeClientMock-1.0.3.1.dist-info/DESCRIPTION.rst
AerospikeClientMock-1.0.3.1.dist-info/METADATA
AerospikeClientMock-1.0.3.1.dist-info/RECORD
AerospikeClientMock-1.0.3.1.dist-info/WHEEL
AerospikeClientMock-1.0.3.1.dist-info/metadata.json
AerospikeClientMock-1.0.3.1.dist-info/top_level.txt
