Metadata-Version: 2.0
Name: AerospikeClientMock
Version: 1.0.3.1
Summary: Aerospike client mock
Home-page: https://github.com/tivvit/aerospike-client-mock-python
Author: Vit Listik
Author-email: tivvit@seznam.cz
License: MIT
Keywords: Aerospike client test testing mock
Platform: UNKNOWN
Classifier: Development Status :: 5 - Production/Stable
Classifier: Intended Audience :: Developers
Classifier: Topic :: Software Development :: Testing
Classifier: License :: OSI Approved :: MIT License
Classifier: Programming Language :: Python :: 2
Classifier: Programming Language :: Python :: 2.6
Classifier: Programming Language :: Python :: 2.7
Classifier: Programming Language :: Python :: 3
Classifier: Programming Language :: Python :: 3.2
Classifier: Programming Language :: Python :: 3.3
Classifier: Programming Language :: Python :: 3.4
Classifier: Programming Language :: Python :: 3.5
Classifier: Programming Language :: Python :: Implementation :: PyPy
